{
	"document_title": "Recommended udpate for SUSE Manager Client Tools",
	"document_type": "SUSE Patch",
	"document_publisher": {
		"type": "Vendor",
		"contact_details": "security@suse.de",
		"issuing_authority": "SUSE Security Team"
	},
	"document_tracking": {
		"identification": {
			"id": "SUSE-SU-2016:1366-1"
		},
		"status": "Final",
		"version": "1",
		"revision_history": {
			"revision": {
				"number": "1",
				"date": "2016-05-19T20:37:14Z",
				"description": "current"
			}
		},
		"initial_release_date": "2016-05-19T20:37:14Z",
		"current_release_date": "2016-05-19T20:37:14Z",
		"generator": {
			"engine": "cve-database/bin/generate-cvrf.pl",
			"date": "2017-02-24T01:00:00Z"
		}
	},
	"document_notes": [
		{
			"text": "Recommended udpate for SUSE Manager Client Tools",
			"title": "Topic",
			"type": "Summary"
		},
		{
			"text": "\nThis update for SUSE Manager Client Tools provides the following fixes and enhancements:\n\nrhnlib:\n\n- Use TLSv1_METHOD in SSL Context (bsc#970989)\n\nsuseRegisterInfo:\n\n- Fix file permissions (bsc#970550)\n",
			"title": "Details",
			"type": "General"
		},
		{
			"text": "The CVRF data is provided by SUSE under the Creative Commons License 4.0 with Attribution (CC-BY-4.0).",
			"title": "Terms of Use",
			"type": "Legal Disclaimer"
		},
		{
			"text": "slessp4-client-tools-21-201602-12567",
			"title": "Patchnames",
			"type": "Details"
		}
	],
	"documentdistribution": "Copyright SUSE LLC under the Creative Commons License 4.0 with Attribution (CC-BY-4.0)",
	"document_references": [
		{
			"type": "Self",
			"url": "https://www.suse.com/support/update/announcement/2016/suse-su-20161366-1/",
			"description": "Link for SUSE-SU-2016:1366-1"
		},
		{
			"type": "Self",
			"url": "https://lists.suse.com/pipermail/sle-security-updates/2016-May/002075.html",
			"description": "E-Mail link for SUSE-SU-2016:1366-1"
		},
		{
			"type": "Self",
			"url": "https://www.suse.com/support/security/rating/",
			"description": "SUSE Security Ratings"
		},
		{
			"type": "Self",
			"url": "https://bugzilla.suse.com/970550",
			"description": "SUSE Bug 970550"
		},
		{
			"type": "Self",
			"url": "https://bugzilla.suse.com/970989",
			"description": "SUSE Bug 970989"
		}
	],
	"product_tree": {
		"branch": [
			{
				"type": "Product Family",
				"name": "SUSE Linux Enterprise Server 11 SP4",
				"branch": [
					{
						"type": "Product Name",
						"name": "SUSE Linux Enterprise Server 11 SP4",
						"full_product_name": {
							"text": "SUSE Linux Enterprise Server 11 SP4",
							"product_id": "SUSE Linux Enterprise Server 11 SP4",
							"cpe": "cpe:/o:suse:suse_sles:11:sp4"
						}
					}
				],
				"full_product_name": {}
			},
			{
				"type": "Product Family",
				"name": "SUSE Linux Enterprise Server for SAP Applications 11 SP4",
				"branch": [
					{
						"type": "Product Name",
						"name": "SUSE Linux Enterprise Server for SAP Applications 11 SP4",
						"full_product_name": {
							"text": "SUSE Linux Enterprise Server for SAP Applications 11 SP4",
							"product_id": "SUSE Linux Enterprise Server for SAP Applications 11 SP4",
							"cpe": "cpe:/o:suse:sles_sap:11:sp4"
						}
					}
				],
				"full_product_name": {}
			},
			{
				"type": "Product Version",
				"name": "rhnlib-2.5.69.8-11.2",
				"full_product_name": {
					"text": "rhnlib-2.5.69.8-11.2",
					"product_id": "rhnlib-2.5.69.8-11.2"
				}
			},
			{
				"type": "Product Version",
				"name": "suseRegisterInfo-2.1.12-14.2",
				"full_product_name": {
					"text": "suseRegisterInfo-2.1.12-14.2",
					"product_id": "suseRegisterInfo-2.1.12-14.2"
				}
			}
		],
		"relationship": [
			{
				"product_reference": "rhnlib-2.5.69.8-11.2",
				"relation_type": "Default Component Of",
				"relates_to_product_reference": "SUSE Linux Enterprise Server 11 SP4"
			},
			{
				"product_reference": "suseRegisterInfo-2.1.12-14.2",
				"relation_type": "Default Component Of",
				"relates_to_product_reference": "SUSE Linux Enterprise Server 11 SP4"
			},
			{
				"product_reference": "rhnlib-2.5.69.8-11.2",
				"relation_type": "Default Component Of",
				"relates_to_product_reference": "SUSE Linux Enterprise Server for SAP Applications 11 SP4"
			},
			{
				"product_reference": "suseRegisterInfo-2.1.12-14.2",
				"relation_type": "Default Component Of",
				"relates_to_product_reference": "SUSE Linux Enterprise Server for SAP Applications 11 SP4"
			}
		]
	}
}
