{
	"document_title": "Security update for openssl-ibmca",
	"document_type": "SUSE Patch",
	"document_publisher": {
		"type": "Vendor",
		"contact_details": "security@suse.de",
		"issuing_authority": "SUSE Security Team"
	},
	"document_tracking": {
		"identification": {
			"id": "SUSE-SU-2023:2046-1"
		},
		"status": "Final",
		"version": "1",
		"revision_history": {
			"revision": {
				"number": "1",
				"date": "2023-04-26T15:31:27Z",
				"description": "current"
			}
		},
		"initial_release_date": "2023-04-26T15:31:27Z",
		"current_release_date": "2023-04-26T15:31:27Z",
		"generator": {
			"engine": "cve-database/bin/generate-cvrf.pl",
			"date": "2017-02-24T01:00:00Z"
		}
	},
	"document_notes": [
		{
			"text": "Security update for openssl-ibmca",
			"title": "Topic",
			"type": "Summary"
		},
		{
			"text": "This update for openssl-ibmca fixes the following issues:\n\nUpgraded openssl-ibmca to version 2.4.0 (bsc#1210058) \n\n- Provider: Adjustments for OpenSSL versions 3.1 and 3.2 \n- Provider: Support RSA blinding\n- Provider: Constant-time fixes for RSA PKCS#1 v1.5 and OAEP padding\n- Provider: Support 'implicit rejection' option for RSA PKCS#1 v1.5 padding\n- Provider: Adjustments in OpenSSL config generator and example configs\n- Engine: EC: Cache ICA key in EC_KEY object (performance improvement)\n\n\n- FIPS 140-3: Correct engine handling so only the ciphers selected in the config file are activated (bsc#1210359)\n\n",
			"title": "Details",
			"type": "General"
		},
		{
			"text": "The CVRF data is provided by SUSE under the Creative Commons License 4.0 with Attribution (CC-BY-4.0).",
			"title": "Terms of Use",
			"type": "Legal Disclaimer"
		},
		{
			"text": "SUSE-2023-2046,SUSE-SLE-Micro-5.4-2023-2046,SUSE-SLE-Module-Server-Applications-15-SP4-2023-2046,openSUSE-SLE-15.4-2023-2046",
			"title": "Patchnames",
			"type": "Details"
		}
	],
	"documentdistribution": "Copyright SUSE LLC under the Creative Commons License 4.0 with Attribution (CC-BY-4.0)",
	"document_references": [
		{
			"type": "Self",
			"url": "https://www.suse.com/support/update/announcement/2023/suse-su-20232046-1/",
			"description": "Link for SUSE-SU-2023:2046-1"
		},
		{
			"type": "Self",
			"url": "https://lists.suse.com/pipermail/sle-security-updates/2023-April/014594.html",
			"description": "E-Mail link for SUSE-SU-2023:2046-1"
		},
		{
			"type": "Self",
			"url": "https://www.suse.com/support/security/rating/",
			"description": "SUSE Security Ratings"
		},
		{
			"type": "Self",
			"url": "https://bugzilla.suse.com/1210058",
			"description": "SUSE Bug 1210058"
		},
		{
			"type": "Self",
			"url": "https://bugzilla.suse.com/1210359",
			"description": "SUSE Bug 1210359"
		}
	],
	"product_tree": {
		"branch": [
			{
				"type": "Product Family",
				"name": "SUSE Linux Enterprise Micro 5.4",
				"branch": [
					{
						"type": "Product Name",
						"name": "SUSE Linux Enterprise Micro 5.4",
						"full_product_name": {
							"text": "SUSE Linux Enterprise Micro 5.4",
							"product_id": "SUSE Linux Enterprise Micro 5.4",
							"cpe": "cpe:/o:suse:sle-micro:5.4"
						}
					}
				],
				"full_product_name": {}
			},
			{
				"type": "Product Family",
				"name": "SUSE Linux Enterprise Module for Server Applications 15 SP4",
				"branch": [
					{
						"type": "Product Name",
						"name": "SUSE Linux Enterprise Module for Server Applications 15 SP4",
						"full_product_name": {
							"text": "SUSE Linux Enterprise Module for Server Applications 15 SP4",
							"product_id": "SUSE Linux Enterprise Module for Server Applications 15 SP4",
							"cpe": "cpe:/o:suse:sle-module-server-applications:15:sp4"
						}
					}
				],
				"full_product_name": {}
			},
			{
				"type": "Product Family",
				"name": "openSUSE Leap 15.4",
				"branch": [
					{
						"type": "Product Name",
						"name": "openSUSE Leap 15.4",
						"full_product_name": {
							"text": "openSUSE Leap 15.4",
							"product_id": "openSUSE Leap 15.4",
							"cpe": "cpe:/o:opensuse:leap:15.4"
						}
					}
				],
				"full_product_name": {}
			},
			{
				"type": "Product Version",
				"name": "openssl-ibmca-2.4.0-150400.4.8.1",
				"full_product_name": {
					"text": "openssl-ibmca-2.4.0-150400.4.8.1",
					"product_id": "openssl-ibmca-2.4.0-150400.4.8.1"
				}
			}
		],
		"relationship": [
			{
				"product_reference": "openssl-ibmca-2.4.0-150400.4.8.1",
				"relation_type": "Default Component Of",
				"relates_to_product_reference": "SUSE Linux Enterprise Micro 5.4"
			},
			{
				"product_reference": "openssl-ibmca-2.4.0-150400.4.8.1",
				"relation_type": "Default Component Of",
				"relates_to_product_reference": "SUSE Linux Enterprise Module for Server Applications 15 SP4"
			},
			{
				"product_reference": "openssl-ibmca-2.4.0-150400.4.8.1",
				"relation_type": "Default Component Of",
				"relates_to_product_reference": "openSUSE Leap 15.4"
			}
		]
	}
}
